fluxloop_cli/__init__.py
fluxloop_cli/arg_binder.py
fluxloop_cli/config_loader.py
fluxloop_cli/config_schema.py
fluxloop_cli/constants.py
fluxloop_cli/conversation_supervisor.py
fluxloop_cli/environment.py
fluxloop_cli/input_generator.py
fluxloop_cli/llm_generator.py
fluxloop_cli/main.py
fluxloop_cli/project_paths.py
fluxloop_cli/runner.py
fluxloop_cli/target_loader.py
fluxloop_cli/templates.py
fluxloop_cli/token_usage.py
fluxloop_cli/validators.py
fluxloop_cli/commands/__init__.py
fluxloop_cli/commands/config.py
fluxloop_cli/commands/doctor.py
fluxloop_cli/commands/evaluate.py
fluxloop_cli/commands/generate.py
fluxloop_cli/commands/init.py
fluxloop_cli/commands/parse.py
fluxloop_cli/commands/record.py
fluxloop_cli/commands/run.py
fluxloop_cli/commands/status.py
fluxloop_cli/evaluation/__init__.py
fluxloop_cli/evaluation/artifacts.py
fluxloop_cli/evaluation/config.py
fluxloop_cli/evaluation/llm.py
fluxloop_cli/evaluation/rules.py
fluxloop_cli/evaluation/engine/__init__.py
fluxloop_cli/evaluation/engine/analysis.py
fluxloop_cli/evaluation/engine/core.py
fluxloop_cli/evaluation/engine/success.py
fluxloop_cli/evaluation/engine/reporting/__init__.py
fluxloop_cli/evaluation/engine/reporting/html.py
fluxloop_cli/evaluation/engine/reporting/markdown.py
fluxloop_cli/evaluation/prompts/__init__.py
fluxloop_cli/evaluation/prompts/base.py
fluxloop_cli/evaluation/prompts/information_completeness.py
fluxloop_cli/evaluation/prompts/intent_recognition.py
fluxloop_cli/evaluation/prompts/response_clarity.py
fluxloop_cli/evaluation/prompts/response_consistency.py
fluxloop_cli/evaluation/report/__init__.py
fluxloop_cli/evaluation/report/aggregator.py
fluxloop_cli/evaluation/report/generator.py
fluxloop_cli/evaluation/report/pipeline.py
fluxloop_cli/evaluation/report/renderer.py
fluxloop_cli/evaluation/templates/report.html.j2
fluxloop_cli/testing/__init__.py
fluxloop_cli/testing/pytest_plugin.py
fluxloop_cli/testing/types.py
fluxloop_cli-0.3.0.dist-info/METADATA
fluxloop_cli-0.3.0.dist-info/WHEEL
fluxloop_cli-0.3.0.dist-info/entry_points.txt
fluxloop_cli-0.3.0.dist-info/top_level.txt
fluxloop_cli-0.3.0.dist-info/RECORD
